netbox_nagios/__init__.py
netbox_nagios/livestatus.py
netbox_nagios/template_content.py
netbox_nagios/version.py
netbox_nagios/templates/device_nagios_box.html
netbox_nagios/templates/device_nagios_buttons.html
netbox_nagios/templatetags/__init__.py
netbox_nagios/templatetags/nagios.py
netbox_nagios-0.0.8.dist-info/LICENSE
netbox_nagios-0.0.8.dist-info/METADATA
netbox_nagios-0.0.8.dist-info/WHEEL
netbox_nagios-0.0.8.dist-info/top_level.txt
netbox_nagios-0.0.8.dist-info/RECORD
