Metadata-Version: 2.1
Name: netbox-nagios
Version: 0.0.8
Summary: Netbox Plugin to show Nagios device state in Netbox.
Home-page: https://github.com/hudson-trading/netbox_nagios/
Author: Hudson River Trading LLC
Author-email: opensource@hudson-trading.com
License: New BSD
Platform: UNKNOWN
License-File: LICENSE
